tests/test_api/__init__.py
tests/test_api/__manifest__.py
tests/test_domain/__init__.py
tests/test_domain/__manifest__.py
tests/test_domain/tests/__init__.py
tests/test_domain/tests/test_domain.py
tests/test_enumeration/__init__.py
tests/test_enumeration/__manifest__.py
tests/test_enumeration/models.py
tests/test_enumeration/data/data.xml
tests/test_enumeration/tests/__init__.py
tests/test_enumeration/tests/test_enumeration.py
tests/test_enumeration/views/views.xml
tests/test_field_html_extensions/__init__.py
tests/test_field_html_extensions/__manifest__.py
tests/test_field_html_extensions/tests/__init__.py
tests/test_field_html_extensions/tests/test_field_html_extensions.py
tests/test_fields_integration_with_reports/__init__.py
tests/test_fields_integration_with_reports/__manifest__.py
tests/test_fields_integration_with_reports/tests/__init__.py
tests/test_fields_integration_with_reports/tests/test_report_integration.py
tests/test_localized_dt/__init__.py
tests/test_localized_dt/__manifest__.py
tests/test_localized_dt/tests/__init__.py
tests/test_localized_dt/tests/test_localized_dt.py
tests/test_models/__init__.py
tests/test_models/__manifest__.py
tests/test_models/models.py
tests/test_models/data/data.xml
tests/test_models/tests/__init__.py
tests/test_models/tests/test_xoeuf_models.py
tests/test_monetary/__init__.py
tests/test_monetary/__manifest__.py
tests/test_monetary/models.py
tests/test_monetary/tests/__init__.py
tests/test_monetary/tests/test_monetary.py
tests/test_one2one/__init__.py
tests/test_one2one/__manifest__.py
tests/test_one2one/tests/__init__.py
tests/test_one2one/tests/test_one2one.py
tests/test_property/__init__.py
tests/test_property/__manifest__.py
tests/test_property/models.py
tests/test_property/tests/__init__.py
tests/test_property/tests/test_property.py
tests/test_property/tests/test_property_depends.py
tests/test_pydantic_field/__init__.py
tests/test_pydantic_field/__manifest__.py
tests/test_pydantic_field/models.py
xoeuf-3.1.0.dist-info/METADATA
xoeuf-3.1.0.dist-info/WHEEL
xoeuf-3.1.0.dist-info/entry_points.txt
xoeuf-3.1.0.dist-info/licenses/LICENSE
xoeuf-3.1.0.dist-info/RECORD
